zhizengzeng/__init__.py
zhizengzeng/zhizengzeng.py
zhizengzeng-0.1.1.dist-info/METADATA
zhizengzeng-0.1.1.dist-info/WHEEL
zhizengzeng-0.1.1.dist-info/top_level.txt
zhizengzeng-0.1.1.dist-info/RECORD
