Metadata-Version: 2.1
Name: zhizengzeng
Version: 0.1.1
Summary: A 3rd party SDK for ZhiZengZeng AI
Home-page: https://github.com/0x24a/zhizengzeng
Author: 0x24a
Author-email: tanhanze@qq.com
Classifier: Programming Language :: Python :: 3
Classifier: License :: OSI Approved :: MIT License
Classifier: Operating System :: OS Independent
Requires-Python: >=3.7
